anwdlserver/__init__.py
anwdlserver/cli.py
anwdlserver/config.py
anwdlserver/process.py
anwdlserver/core/__init__.py
anwdlserver/core/client.py
anwdlserver/core/crypto.py
anwdlserver/core/database.py
anwdlserver/core/sanitize.py
anwdlserver/core/server.py
anwdlserver/core/util.py
anwdlserver/core/virtualization.py
anwdlserver/tools/__init__.py
anwdlserver/tools/accesstk.py
anwdlserver-1.1.6.dist-info/LICENSE
anwdlserver-1.1.6.dist-info/METADATA
anwdlserver-1.1.6.dist-info/WHEEL
anwdlserver-1.1.6.dist-info/entry_points.txt
anwdlserver-1.1.6.dist-info/top_level.txt
anwdlserver-1.1.6.dist-info/RECORD
