Metadata-Version: 2.1
Name: anwdlserver
Version: 1.1.6
Summary: The Anweddol server implementation
Home-page: https://github.com/the-anweddol-project/Anweddol-server
Author: The Anweddol project
Author-email: The Anweddol project <the-anweddol-project@proton.me>
License: GNU GENERAL PUBLIC LICENSE
Project-URL: Homepage, https://github.com/the-anweddol-project/Anweddol-server
Project-URL: Bug Tracker, https://github.com/the-anweddol-project/Anweddol-server/issues
Classifier: Development Status :: 4 - Beta
Classifier: License :: OSI Approved :: GNU General Public License v3 or later (GPLv3+)
Classifier: Intended Audience :: Developers
Classifier: Intended Audience :: End Users/Desktop
Classifier: Programming Language :: Python :: 3
Classifier: Topic :: Internet
Classifier: Topic :: System :: Emulators
License-File: LICENSE
Requires-Dist: cryptography
Requires-Dist: paramiko
Requires-Dist: python-daemon
Requires-Dist: cerberus
Requires-Dist: defusedxml
Requires-Dist: sqlalchemy
Requires-Dist: pyyaml
